{
  "path_loss_parameters": {
    "path_loss_exponent": 3.5,
    "shadowing_sigma": 6.0,
    "path_loss_at_reference_distance": 32.0,
    "noise_floor": -117.0
  },
  "lora_parameters": {
    "bandwidth": 250000,
    "spreading_factor": 7,
    "coding_rate": 1,
    "preamble_symbols": 8.0,
    "crc_enabled": true,
    "low_data_rate_optimization": false
  },
    "radio_module_config": {
    "delay_between_tx_packets": 200,
    "delay_between_tx_messages": 5,
    "echo_request_minimal_interval": 3,
    "echo_messages_target_interval": 100,
    "echo_gathering_timeout": 1,
    "relay_position_delay": 1,
    "scoring_matrix": [173, 242, 49, 123, 42],
    "retry_interval_for_missing_packets": 60,
    "tx_maximum_random_delay": 200
  },
  "nodes": [
    {"node_id": 1, "position": {"y": 47.39910309690799, "x": 18.944571384188297}, "radio_strength": 20},
    {"node_id": 2, "position": {"y": 47.39867465757536, "x": 18.933823122072507}, "radio_strength": 20},
    {"node_id": 3, "position": {"y": 47.40948576736744, "x": 18.927653371592204}, "radio_strength": 20},
    {"node_id": 4, "position": {"y": 47.41433171718669, "x": 18.92776999496779}, "radio_strength": 20},
    {"node_id": 5, "position": {"y": 47.410858104830666, "x": 18.92912515729761}, "radio_strength": 20},
    {"node_id": 6, "position": {"y": 47.40755387875003, "x": 18.93680876050758}, "radio_strength": 20},
    {"node_id": 7, "position": {"y": 47.39394522779959, "x": 18.944750271160743}, "radio_strength": 20}
  ],
  "obstacles": [],
  "world_top_left": { "y": 47.420777920359676, "x": 18.91532117376626 },
  "world_bottom_right": { "y": 47.3909453611854, "x": 18.96701416893434 },
  "width": 3859,
  "height": 3300,
  "background_image": "background.png"
}
